barrack/Medic.py
barrack/__init__.py
KNUE_Programming-0.0.2.dist-info/LICENSE
KNUE_Programming-0.0.2.dist-info/METADATA
KNUE_Programming-0.0.2.dist-info/WHEEL
KNUE_Programming-0.0.2.dist-info/top_level.txt
KNUE_Programming-0.0.2.dist-info/RECORD
